pyunite/__init__.py
pyunite/__main__.py
pyunite/cli.py
pyUnite-0.0.0a0.dist-info/LICENSE
pyUnite-0.0.0a0.dist-info/METADATA
pyUnite-0.0.0a0.dist-info/WHEEL
pyUnite-0.0.0a0.dist-info/entry_points.txt
pyUnite-0.0.0a0.dist-info/top_level.txt
pyUnite-0.0.0a0.dist-info/RECORD
