Metadata-Version: 2.1
Name: pyUnite
Version: 0.0.0a0
Summary: Unite all of your python files into one single file
Author-email: Riley <riley@riley0122.dev>
Project-URL: Homepage, https://github.com/riley0122/pyunite
Project-URL: Issues, https://github.com/riley0122/pyunite/issues
Classifier: Programming Language :: Python :: 3
Classifier: License :: OSI Approved :: Mozilla Public License 2.0 (MPL 2.0)
Classifier: Operating System :: OS Independent
Classifier: Development Status :: 3 - Alpha
Classifier: Environment :: Console
Classifier: Intended Audience :: Developers
Requires-Python: >=3.0
License-File: LICENSE
